json_timeseries/__init__.py
json_timeseries/jts.py
tests/__init__.py
tests/test_json_timeseries.py
json_timeseries-0.1.7.dist-info/LICENSE
json_timeseries-0.1.7.dist-info/METADATA
json_timeseries-0.1.7.dist-info/WHEEL
json_timeseries-0.1.7.dist-info/top_level.txt
json_timeseries-0.1.7.dist-info/RECORD
