Metadata-Version: 2.1
Name: json_timeseries
Version: 0.1.7
Summary: JSON-TimeSeries (JTS specification) handling library
Home-page: https://github.com/slaxor505/json-timeseries-py
Author: Slava Pisarevskiy
Author-email: slava@plantbook.io
License: MIT
Project-URL: Documentation, https://json-timeseries-py.readthedocs.io
Project-URL: Source, https://github.com/slaxor505/json-timeseries-py
Project-URL: Specification, https://docs.eagle.io/en/latest/reference/historic/jts.html
Keywords: json,timeseries,iot,jts
Classifier: Intended Audience :: Developers
Classifier: License :: OSI Approved :: MIT License
Classifier: Programming Language :: Python
Classifier: Programming Language :: Python :: 3
Classifier: Programming Language :: Python :: 3.9
Classifier: Operating System :: OS Independent
Requires-Python: >=3.9
License-File: LICENSE
Requires-Dist: python-dateutil
